pyevilgenius/__init__.py
pyevilgenius-2.0.0.dist-info/LICENSE
pyevilgenius-2.0.0.dist-info/METADATA
pyevilgenius-2.0.0.dist-info/WHEEL
pyevilgenius-2.0.0.dist-info/top_level.txt
pyevilgenius-2.0.0.dist-info/zip-safe
pyevilgenius-2.0.0.dist-info/RECORD
