Metadata-Version: 2.1
Name: pyevilgenius
Version: 2.0.0
Summary: Python module to talk to Evil Genius Labs devices.
Home-page: https://github.com/home-assistant-libs/pyevilgenius
Author: Paulus Schoutsen
Author-email: paulus@paulusschoutsen.nl
License: Apache License 2.0
Platform: any
Classifier: Intended Audience :: Developers
Classifier: Operating System :: OS Independent
Classifier: Programming Language :: Python
Classifier: Programming Language :: Python :: 3
Classifier: Topic :: Software Development :: Libraries :: Python Modules
License-File: LICENSE
